{"ticker": "AAPL", "expiry": "20260220", "asof": "20260219", "cached_at": "2026-02-20T19:45:58.116317+00:00", "rows": [{"strike": 230.0, "pRN": 0.958064}, {"strike": 235.0, "pRN": 0.958064}, {"strike": 240.0, "pRN": 0.958064}, {"strike": 245.0, "pRN": 0.958064}, {"strike": 250.0, "pRN": 0.940077}, {"strike": 255.0, "pRN": 0.895074}, {"strike": 260.0, "pRN": 0.588048}, {"strike": 265.0, "pRN": 0.157013}, {"strike": 270.0, "pRN": 0.018001}, {"strike": 275.0, "pRN": 0.006}, {"strike": 280.0, "pRN": 0.0}, {"strike": 285.0, "pRN": 0.0}, {"strike": 290.0, "pRN": 0.0}]}